{
  "folder": "label_files",
  "filename": "former1_44_0R",
  "path": "D:\\Laser_controller_new_combined\\full_data_set\\label_files\\former1_44_0R.json",
  "objects": [
    {
      "name": "finger_1",
      "centroid": {
        "x": -6.327102390113941,
        "y": -10.243535343629661,
        "z": -10.82925788
      },
      "dimensions": {
        "length": 8.0,
        "width": 5.0,
        "height": 12.0
      },
      "rotations": {
        "x": 0,
        "y": 12.999999999999993,
        "z": 0
      }
    },
    {
      "name": "finger_2",
      "centroid": {
        "x": 1.4161749475855743,
        "y": -6.3535458357490295,
        "z": 3.0835316099999996
      },
      "dimensions": {
        "length": 12.0,
        "width": 4.0,
        "height": 10.0
      },
      "rotations": {
        "x": 0,
        "y": 13.000000000000004,
        "z": 0
      }
    },
    {
      "name": "finger_3",
      "centroid": {
        "x": 3.709518449259546,
        "y": -2.2303723347124373,
        "z": 3.4768925
      },
      "dimensions": {
        "length": 12.0,
        "width": 4.0,
        "height": 10.0
      },
      "rotations": {
        "x": 0,
        "y": 12.999999999999991,
        "z": 0
      }
    },
    {
      "name": "finger_4",
      "centroid": {
        "x": 4.148713631729479,
        "y": 3.099936926980044,
        "z": 3.66544134
      },
      "dimensions": {
        "length": 12.0,
        "width": 4.0,
        "height": 10.0
      },
      "rotations": {
        "x": 0,
        "y": 13.000000000000016,
        "z": 0
      }
    },
    {
      "name": "finger_5",
      "centroid": {
        "x": 2.987673798107559,
        "y": 8.239099957211465,
        "z": 0.8977889800000001
      },
      "dimensions": {
        "length": 9.0,
        "width": 3.5,
        "height": 10.0
      },
      "rotations": {
        "x": 0,
        "y": 13.000000000000009,
        "z": 0
      }
    }
  ]
}