{
  "folder": "label_files",
  "filename": "former3_151_3L",
  "path": "D:\\Laser_controller_new_combined\\full_data_set\\label_files\\former3_151_3L.json",
  "objects": [
    {
      "name": "finger_4",
      "centroid": {
        "x": 1.919946181788827,
        "y": -3.6110973133267703,
        "z": 5.41172147
      },
      "dimensions": {
        "length": 13.0,
        "width": 3.0,
        "height": 12.0
      },
      "rotations": {
        "x": 0,
        "y": 20.000000000000004,
        "z": 0
      }
    },
    {
      "name": "finger_5",
      "centroid": {
        "x": -0.2222304561562749,
        "y": -6.626823548242856,
        "z": 4.49353466
      },
      "dimensions": {
        "length": 11.0,
        "width": 3.0,
        "height": 12.0
      },
      "rotations": {
        "x": 0,
        "y": 20.000000000000004,
        "z": 0
      }
    },
    {
      "name": "finger_3",
      "centroid": {
        "x": 3.3585913819969817,
        "y": -0.635178326018748,
        "z": 5.31148938
      },
      "dimensions": {
        "length": 14.0,
        "width": 3.5,
        "height": 12.0
      },
      "rotations": {
        "x": 0,
        "y": 20.000000000000007,
        "z": 0
      }
    },
    {
      "name": "finger_2",
      "centroid": {
        "x": 3.859854125238463,
        "y": 3.107719763115075,
        "z": 5.61955684
      },
      "dimensions": {
        "length": 12.0,
        "width": 3.5,
        "height": 12.0
      },
      "rotations": {
        "x": 0,
        "y": 19.99999999999998,
        "z": 0
      }
    },
    {
      "name": "finger_1",
      "centroid": {
        "x": -1.0512081170022518,
        "y": 9.405631049278915,
        "z": -6.35543872
      },
      "dimensions": {
        "length": 10.0,
        "width": 4.0,
        "height": 12.0
      },
      "rotations": {
        "x": 0,
        "y": 19.999999999999986,
        "z": 0
      }
    }
  ]
}