{
  "folder": "label_files",
  "filename": "former3_124_1R",
  "path": "D:\\Laser_controller_new_combined\\full_data_set\\label_files\\former3_124_1R.json",
  "objects": [
    {
      "name": "finger_1",
      "centroid": {
        "x": -3.055475087421879,
        "y": -11.376693341768242,
        "z": -6.029138438527259
      },
      "dimensions": {
        "length": 10.0,
        "width": 4.5,
        "height": 8.0
      },
      "rotations": {
        "x": 352.0,
        "y": 18.165328985758435,
        "z": 2.5891559744003088
      }
    },
    {
      "name": "finger_2",
      "centroid": {
        "x": 5.068144857596504,
        "y": -5.113040174580625,
        "z": 4.715426655756196
      },
      "dimensions": {
        "length": 12.5,
        "width": 4.0,
        "height": 10.0
      },
      "rotations": {
        "x": 352.0,
        "y": 18.165328985758435,
        "z": 2.5891559744003056
      }
    },
    {
      "name": "finger_3",
      "centroid": {
        "x": 8.030380976340805,
        "y": -1.0100516492478842,
        "z": 4.221066126797364
      },
      "dimensions": {
        "length": 11.0,
        "width": 4.0,
        "height": 10.0
      },
      "rotations": {
        "x": 352.0,
        "y": 18.16532898575844,
        "z": 2.589155974400312
      }
    },
    {
      "name": "finger_4",
      "centroid": {
        "x": 9.16339116960743,
        "y": 3.633918959727775,
        "z": 3.533643133058286
      },
      "dimensions": {
        "length": 11.0,
        "width": 4.0,
        "height": 10.0
      },
      "rotations": {
        "x": 352.0,
        "y": 18.165328985758432,
        "z": 2.5891559744003017
      }
    },
    {
      "name": "finger_5",
      "centroid": {
        "x": 8.513126617921573,
        "y": 8.676682534750633,
        "z": 1.36495058208717
      },
      "dimensions": {
        "length": 10.0,
        "width": 4.0,
        "height": 11.0
      },
      "rotations": {
        "x": 352.0,
        "y": 18.165328985758435,
        "z": 2.5891559744003056
      }
    }
  ]
}